combine/__init__.py
combine/base_content/error.template.html
combine/base_content/markdown.template.html
combine/base_content/redirect.template.html
combine/checks/__init__.py
combine/checks/base.py
combine/checks/duplicate_id.py
combine/checks/favicon.py
combine/checks/file_size.py
combine/checks/img_alt.py
combine/checks/issues.py
combine/checks/links.py
combine/checks/meta.py
combine/checks/mixed_content.py
combine/checks/open_graph.py
combine/checks/title.py
combine/cli.py
combine/config.py
combine/core.py
combine/dev.py
combine/exceptions.py
combine/files/__init__.py
combine/files/core.py
combine/files/error.py
combine/files/html.py
combine/files/ignored.py
combine/files/keep.py
combine/files/markdown.py
combine/files/redirect.py
combine/files/template.py
combine/files/utils.py
combine/jinja/__init__.py
combine/jinja/code.py
combine/jinja/exceptions.py
combine/jinja/include_raw.py
combine/jinja/markdown.py
combine/jinja/references.py
combine/jinja/urls.py
combine/logger.py
combine-2.17.0.dist-info/LICENSE
combine-2.17.0.dist-info/METADATA
combine-2.17.0.dist-info/WHEEL
combine-2.17.0.dist-info/entry_points.txt
combine-2.17.0.dist-info/RECORD
