Metadata-Version: 2.1
Name: combine
Version: 2.17.0
Summary: A straightforward static site builder.
Home-page: https://combine.dropseed.dev
License: MIT
Keywords: static,site,generator,jinja
Author: Dropseed
Author-email: python@dropseed.dev
Requires-Python: >=3.8.0,<4.0.0
Classifier: License :: OSI Approved :: MIT License
Classifier: Programming Language :: Python :: 3
Classifier: Programming Language :: Python :: 3.8
Classifier: Programming Language :: Python :: 3.9
Classifier: Programming Language :: Python :: 3.10
Classifier: Programming Language :: Python :: 3.11
Classifier: Programming Language :: Python :: 3.12
Classifier: Programming Language :: Python :: 3.13
Requires-Dist: Jinja2 (>=3.1.2,<4.0.0)
Requires-Dist: PyYAML (>=6.0,<7.0)
Requires-Dist: Pygments (>=2.6.1,<3.0.0)
Requires-Dist: barrel (>=0.3.0,<0.4.0)
Requires-Dist: beautifulsoup4 (>=4.9.1,<5.0.0)
Requires-Dist: click (>7.1.2)
Requires-Dist: honcho (>=1.1.0,<2.0.0)
Requires-Dist: markdown (>=3.2.2,<4.0.0)
Requires-Dist: python-frontmatter (>=1.0.0,<2.0.0)
Requires-Dist: repaint (>=0.1.0,<0.2.0)
Requires-Dist: typing-extensions (>=4.3.0,<5.0.0)
Requires-Dist: watchfiles (>=0.19.0,<0.20.0)
Project-URL: Documentation, https://combine.dropseed.dev
Project-URL: Repository, https://github.com/dropseed/combine
